pycocotools-2.0.9.dist-info/RECORD
pycocotools-2.0.9.dist-info/WHEEL
pycocotools-2.0.9.dist-info/top_level.txt
pycocotools-2.0.9.dist-info/METADATA
pycocotools/coco.py
pycocotools/mask.py
pycocotools/_mask.cpython-312-darwin.so
pycocotools/__init__.py
pycocotools/cocoeval.py
